myac/LICENSE.txt
myac/__init__.py
myac/myac.py
myac-0.0.0.post1.dist-info/METADATA
myac-0.0.0.post1.dist-info/WHEEL
myac-0.0.0.post1.dist-info/top_level.txt
myac-0.0.0.post1.dist-info/RECORD
