Metadata-Version: 2.1
Name: myac
Version: 0.0.0.post1
Summary: myac
Author-email: Ruud van der Ham <rt.van.der.ham@gmail.com>
Project-URL: Homepage, https://github.com/salabim/myac
Project-URL: Repository, https://github.com/salabim/myac
Classifier: Development Status :: 5 - Production/Stable
Classifier: License :: OSI Approved :: MIT License
Classifier: Programming Language :: Python :: 3 :: Only
Requires-Python: >=3.7
